jira_tool/__init__.py
jira_tool/console_script.py
jira_tool/excel_definition.py
jira_tool/excel_operation.py
jira_tool/jira_client.py
jira_tool/milestone.py
jira_tool/priority.py
jira_tool/sprint_schedule.py
jira_tool/story.py
jira_tool/assets/excel_definition.json
jira_tool/assets/sprint_schedule.json
sharry_jira_tool-1.0.0.dist-info/licenses/LICENSE
sharry_jira_tool-1.0.0.dist-info/METADATA
sharry_jira_tool-1.0.0.dist-info/WHEEL
sharry_jira_tool-1.0.0.dist-info/top_level.txt
sharry_jira_tool-1.0.0.dist-info/RECORD
