Metadata-Version: 2.4
Name: sharry-jira-tool
Version: 1.0.0
Summary: Sort Jira stories in Excel
Author-email: Sharry Xu <sharry.xu@outlook.com>
License: MIT License
Project-URL: Homepage, https://github.com/jira-assistant/jira-tool
Keywords: jira,excel,jira-cloud
Classifier: License :: OSI Approved :: MIT License
Classifier: Programming Language :: Python
Classifier: Programming Language :: Python :: 3
Requires-Python: >=3.10
License-File: LICENSE
Requires-Dist: jira-assistant>=1.0.3
Provides-Extra: dev
Requires-Dist: pip-tools; extra == "dev"
Requires-Dist: pytest; extra == "dev"
Dynamic: license-file
